[
    {
        "jmhVersion" : "1.35",
        "benchmark" : "javalin.performance.JavalinBenchmark.hello",
        "mode" : "thrpt",
        "threads" : 4,
        "forks" : 2,
        "jvm" : "/usr/lib/jvm/temurin-17-jdk-amd64/bin/java",
        "jvmArgs" : [
            "-Dforks=2",
            "-DiterationTime=1000",
            "-Diterations=10",
            "-Dmode=benchmark",
            "-DprofileName",
            "-DresultFormat=json",
            "-Dthreads=4",
            "-Dversion=7.0.1",
            "-Dfile.encoding=UTF-8",
            "-Duser.country",
            "-Duser.language=en",
            "-Duser.variant"
        ],
        "jdkVersion" : "17.0.18",
        "vmName" : "OpenJDK 64-Bit Server VM",
        "vmVersion" : "17.0.18+8",
        "warmupIterations" : 10,
        "warmupTime" : "1000 ms",
        "warmupBatchSize" : 1,
        "measurementIterations" : 10,
        "measurementTime" : "1000 ms",
        "measurementBatchSize" : 1,
        "primaryMetric" : {
            "score" : 7.243788399477131,
            "scoreError" : 0.04596247274927082,
            "scoreConfidence" : [
                7.19782592672786,
                7.289750872226402
            ],
            "scorePercentiles" : {
                "0.0" : 7.1454785438224455,
                "50.0" : 7.234092447709157,
                "90.0" : 7.3111146487790455,
                "95.0" : 7.318329819283525,
                "99.0" : 7.318701582975359,
                "99.9" : 7.318701582975359,
                "99.99" : 7.318701582975359,
                "99.999" : 7.318701582975359,
                "99.9999" : 7.318701582975359,
                "100.0" : 7.318701582975359
            },
            "scoreUnit" : "ops/ms",
            "rawData" : [
                [
                    7.188968259221374,
                    7.2093445053143315,
                    7.218163065313105,
                    7.244807959490078,
                    7.223376935928237,
                    7.188655641648693,
                    7.247526189003747,
                    7.2059225588310305,
                    7.206238951100423,
                    7.175741155775626
                ],
                [
                    7.215176589166319,
                    7.289834361945414,
                    7.1454785438224455,
                    7.311266309138671,
                    7.289985263010761,
                    7.304804135492558,
                    7.318701582975359,
                    7.291041070788902,
                    7.29098520603311,
                    7.309749705542416
                ]
            ]
        },
        "secondaryMetrics" : {
        }
    },
    {
        "jmhVersion" : "1.35",
        "benchmark" : "javalin.performance.JavalinBenchmark.jsonSerialization100kb",
        "mode" : "thrpt",
        "threads" : 4,
        "forks" : 2,
        "jvm" : "/usr/lib/jvm/temurin-17-jdk-amd64/bin/java",
        "jvmArgs" : [
            "-Dforks=2",
            "-DiterationTime=1000",
            "-Diterations=10",
            "-Dmode=benchmark",
            "-DprofileName",
            "-DresultFormat=json",
            "-Dthreads=4",
            "-Dversion=7.0.1",
            "-Dfile.encoding=UTF-8",
            "-Duser.country",
            "-Duser.language=en",
            "-Duser.variant"
        ],
        "jdkVersion" : "17.0.18",
        "vmName" : "OpenJDK 64-Bit Server VM",
        "vmVersion" : "17.0.18+8",
        "warmupIterations" : 10,
        "warmupTime" : "1000 ms",
        "warmupBatchSize" : 1,
        "measurementIterations" : 10,
        "measurementTime" : "1000 ms",
        "measurementBatchSize" : 1,
        "primaryMetric" : {
            "score" : 2.23588857948193,
            "scoreError" : 0.024506007392311874,
            "scoreConfidence" : [
                2.2113825720896183,
                2.260394586874242
            ],
            "scorePercentiles" : {
                "0.0" : 2.133230847095235,
                "50.0" : 2.241495755914389,
                "90.0" : 2.2583253120944975,
                "95.0" : 2.266925706564453,
                "99.0" : 2.267377041313107,
                "99.9" : 2.267377041313107,
                "99.99" : 2.267377041313107,
                "99.999" : 2.267377041313107,
                "99.9999" : 2.267377041313107,
                "100.0" : 2.267377041313107
            },
            "scoreUnit" : "ops/ms",
            "rawData" : [
                [
                    2.133230847095235,
                    2.2213299483379005,
                    2.2268667991362334,
                    2.2424497352074133,
                    2.231723858418372,
                    2.241094640423176,
                    2.2064868505516673,
                    2.2418968714056016,
                    2.2229625191025657,
                    2.239713303311922
                ],
                [
                    2.252716833205275,
                    2.2369342634677563,
                    2.2419922567674204,
                    2.2581000038847314,
                    2.267377041313107,
                    2.258350346340027,
                    2.2394923826932795,
                    2.246962884486858,
                    2.2575540643139185,
                    2.250536140176138
                ]
            ]
        },
        "secondaryMetrics" : {
        }
    },
    {
        "jmhVersion" : "1.35",
        "benchmark" : "javalin.performance.JavalinBenchmark.jsonSerialization1mb",
        "mode" : "thrpt",
        "threads" : 4,
        "forks" : 2,
        "jvm" : "/usr/lib/jvm/temurin-17-jdk-amd64/bin/java",
        "jvmArgs" : [
            "-Dforks=2",
            "-DiterationTime=1000",
            "-Diterations=10",
            "-Dmode=benchmark",
            "-DprofileName",
            "-DresultFormat=json",
            "-Dthreads=4",
            "-Dversion=7.0.1",
            "-Dfile.encoding=UTF-8",
            "-Duser.country",
            "-Duser.language=en",
            "-Duser.variant"
        ],
        "jdkVersion" : "17.0.18",
        "vmName" : "OpenJDK 64-Bit Server VM",
        "vmVersion" : "17.0.18+8",
        "warmupIterations" : 10,
        "warmupTime" : "1000 ms",
        "warmupBatchSize" : 1,
        "measurementIterations" : 10,
        "measurementTime" : "1000 ms",
        "measurementBatchSize" : 1,
        "primaryMetric" : {
            "score" : 0.2363973297926793,
            "scoreError" : 0.008481736566597507,
            "scoreConfidence" : [
                0.2279155932260818,
                0.2448790663592768
            ],
            "scorePercentiles" : {
                "0.0" : 0.21915228645512985,
                "50.0" : 0.23707840911527978,
                "90.0" : 0.25199296468324545,
                "95.0" : 0.2529374088082106,
                "99.0" : 0.2529593855382756,
                "99.9" : 0.2529593855382756,
                "99.99" : 0.2529593855382756,
                "99.999" : 0.2529593855382756,
                "99.9999" : 0.2529593855382756,
                "100.0" : 0.2529593855382756
            },
            "scoreUnit" : "ops/ms",
            "rawData" : [
                [
                    0.23044973074557043,
                    0.22184524027860866,
                    0.21986311525184882,
                    0.2317678435219768,
                    0.2256885192711475,
                    0.23406862797160027,
                    0.2472509883996773,
                    0.23717321233867025,
                    0.25251985093697527,
                    0.24114654823950735
                ],
                [
                    0.24181228706426075,
                    0.2421999862066579,
                    0.21915228645512985,
                    0.23424622977845602,
                    0.23276496702940094,
                    0.2427812665915624,
                    0.2369836058918893,
                    0.24242982848136307,
                    0.2529593855382756,
                    0.2408430758610085
                ]
            ]
        },
        "secondaryMetrics" : {
        }
    },
    {
        "jmhVersion" : "1.35",
        "benchmark" : "javalin.performance.JavalinBenchmark.jsonSerializationSmall",
        "mode" : "thrpt",
        "threads" : 4,
        "forks" : 2,
        "jvm" : "/usr/lib/jvm/temurin-17-jdk-amd64/bin/java",
        "jvmArgs" : [
            "-Dforks=2",
            "-DiterationTime=1000",
            "-Diterations=10",
            "-Dmode=benchmark",
            "-DprofileName",
            "-DresultFormat=json",
            "-Dthreads=4",
            "-Dversion=7.0.1",
            "-Dfile.encoding=UTF-8",
            "-Duser.country",
            "-Duser.language=en",
            "-Duser.variant"
        ],
        "jdkVersion" : "17.0.18",
        "vmName" : "OpenJDK 64-Bit Server VM",
        "vmVersion" : "17.0.18+8",
        "warmupIterations" : 10,
        "warmupTime" : "1000 ms",
        "warmupBatchSize" : 1,
        "measurementIterations" : 10,
        "measurementTime" : "1000 ms",
        "measurementBatchSize" : 1,
        "primaryMetric" : {
            "score" : 21.6576601179769,
            "scoreError" : 0.11458399871477255,
            "scoreConfidence" : [
                21.54307611926213,
                21.77224411669167
            ],
            "scorePercentiles" : {
                "0.0" : 21.28082890275411,
                "50.0" : 21.64919477214908,
                "90.0" : 21.853843362805133,
                "95.0" : 21.871763804926925,
                "99.0" : 21.87251890151954,
                "99.9" : 21.87251890151954,
                "99.99" : 21.87251890151954,
                "99.999" : 21.87251890151954,
                "99.9999" : 21.87251890151954,
                "100.0" : 21.87251890151954
            },
            "scoreUnit" : "ops/ms",
            "rawData" : [
                [
                    21.644309503592044,
                    21.59744404862995,
                    21.85741696966724,
                    21.82168090104617,
                    21.483688860780894,
                    21.639205373952066,
                    21.586414132410926,
                    21.736721871783832,
                    21.767918423703396,
                    21.87251890151954
                ],
                [
                    21.71258649626978,
                    21.6259298877053,
                    21.596390222752113,
                    21.654080040706113,
                    21.669357209565245,
                    21.63780922222918,
                    21.28082890275411,
                    21.720767833672376,
                    21.582813279172363,
                    21.66532027762529
                ]
            ]
        },
        "secondaryMetrics" : {
        }
    },
    {
        "jmhVersion" : "1.35",
        "benchmark" : "javalin.performance.JavalinBenchmark.payload100kb",
        "mode" : "thrpt",
        "threads" : 4,
        "forks" : 2,
        "jvm" : "/usr/lib/jvm/temurin-17-jdk-amd64/bin/java",
        "jvmArgs" : [
            "-Dforks=2",
            "-DiterationTime=1000",
            "-Diterations=10",
            "-Dmode=benchmark",
            "-DprofileName",
            "-DresultFormat=json",
            "-Dthreads=4",
            "-Dversion=7.0.1",
            "-Dfile.encoding=UTF-8",
            "-Duser.country",
            "-Duser.language=en",
            "-Duser.variant"
        ],
        "jdkVersion" : "17.0.18",
        "vmName" : "OpenJDK 64-Bit Server VM",
        "vmVersion" : "17.0.18+8",
        "warmupIterations" : 10,
        "warmupTime" : "1000 ms",
        "warmupBatchSize" : 1,
        "measurementIterations" : 10,
        "measurementTime" : "1000 ms",
        "measurementBatchSize" : 1,
        "primaryMetric" : {
            "score" : 2.7380615217217263,
            "scoreError" : 0.014276883154336057,
            "scoreConfidence" : [
                2.7237846385673903,
                2.7523384048760624
            ],
            "scorePercentiles" : {
                "0.0" : 2.6809516101578885,
                "50.0" : 2.7425320497871626,
                "90.0" : 2.7523286929285233,
                "95.0" : 2.7582036584002427,
                "99.0" : 2.7585086593547214,
                "99.9" : 2.7585086593547214,
                "99.99" : 2.7585086593547214,
                "99.999" : 2.7585086593547214,
                "99.9999" : 2.7585086593547214,
                "100.0" : 2.7585086593547214
            },
            "scoreUnit" : "ops/ms",
            "rawData" : [
                [
                    2.731473520843207,
                    2.7494668096846495,
                    2.746886624859685,
                    2.7439662236947937,
                    2.7223084044071637,
                    2.7427560925258865,
                    2.7305999228987394,
                    2.7585086593547214,
                    2.75160916689893,
                    2.73793823041406
                ],
                [
                    2.752408640265145,
                    2.7331154239220443,
                    2.7431628327828594,
                    2.7297394668796007,
                    2.7496749819564297,
                    2.7295778993388176,
                    2.7423080070484382,
                    2.6809516101578885,
                    2.736355833647779,
                    2.748422082853679
                ]
            ]
        },
        "secondaryMetrics" : {
        }
    },
    {
        "jmhVersion" : "1.35",
        "benchmark" : "javalin.performance.JavalinBenchmark.payload1mb",
        "mode" : "thrpt",
        "threads" : 4,
        "forks" : 2,
        "jvm" : "/usr/lib/jvm/temurin-17-jdk-amd64/bin/java",
        "jvmArgs" : [
            "-Dforks=2",
            "-DiterationTime=1000",
            "-Diterations=10",
            "-Dmode=benchmark",
            "-DprofileName",
            "-DresultFormat=json",
            "-Dthreads=4",
            "-Dversion=7.0.1",
            "-Dfile.encoding=UTF-8",
            "-Duser.country",
            "-Duser.language=en",
            "-Duser.variant"
        ],
        "jdkVersion" : "17.0.18",
        "vmName" : "OpenJDK 64-Bit Server VM",
        "vmVersion" : "17.0.18+8",
        "warmupIterations" : 10,
        "warmupTime" : "1000 ms",
        "warmupBatchSize" : 1,
        "measurementIterations" : 10,
        "measurementTime" : "1000 ms",
        "measurementBatchSize" : 1,
        "primaryMetric" : {
            "score" : 0.2926081798152882,
            "scoreError" : 0.02357938819496314,
            "scoreConfidence" : [
                0.26902879162032506,
                0.31618756801025133
            ],
            "scorePercentiles" : {
                "0.0" : 0.2240864701712898,
                "50.0" : 0.30059947757819067,
                "90.0" : 0.31920233249675667,
                "95.0" : 0.3201427086153546,
                "99.0" : 0.32018736647833274,
                "99.9" : 0.32018736647833274,
                "99.99" : 0.32018736647833274,
                "99.999" : 0.32018736647833274,
                "99.9999" : 0.32018736647833274,
                "100.0" : 0.32018736647833274
            },
            "scoreUnit" : "ops/ms",
            "rawData" : [
                [
                    0.28258457250613467,
                    0.29527234464622937,
                    0.290945337581319,
                    0.30773999012226994,
                    0.2994836692986452,
                    0.3066002969865448,
                    0.3153893084605346,
                    0.28344163503123715,
                    0.2256095425164799,
                    0.2240864701712898
                ],
                [
                    0.272112629039054,
                    0.29235831288819436,
                    0.3183754419986343,
                    0.3017152858577361,
                    0.32018736647833274,
                    0.3091324390046046,
                    0.3192942092187703,
                    0.3105805423443165,
                    0.2749783508375554,
                    0.3022758513178811
                ]
            ]
        },
        "secondaryMetrics" : {
        }
    },
    {
        "jmhVersion" : "1.35",
        "benchmark" : "javalin.performance.JavalinBenchmark.payloadEmpty",
        "mode" : "thrpt",
        "threads" : 4,
        "forks" : 2,
        "jvm" : "/usr/lib/jvm/temurin-17-jdk-amd64/bin/java",
        "jvmArgs" : [
            "-Dforks=2",
            "-DiterationTime=1000",
            "-Diterations=10",
            "-Dmode=benchmark",
            "-DprofileName",
            "-DresultFormat=json",
            "-Dthreads=4",
            "-Dversion=7.0.1",
            "-Dfile.encoding=UTF-8",
            "-Duser.country",
            "-Duser.language=en",
            "-Duser.variant"
        ],
        "jdkVersion" : "17.0.18",
        "vmName" : "OpenJDK 64-Bit Server VM",
        "vmVersion" : "17.0.18+8",
        "warmupIterations" : 10,
        "warmupTime" : "1000 ms",
        "warmupBatchSize" : 1,
        "measurementIterations" : 10,
        "measurementTime" : "1000 ms",
        "measurementBatchSize" : 1,
        "primaryMetric" : {
            "score" : 23.340550298475627,
            "scoreError" : 0.16678632563139734,
            "scoreConfidence" : [
                23.17376397284423,
                23.507336624107023
            ],
            "scorePercentiles" : {
                "0.0" : 22.699096518954484,
                "50.0" : 23.38820667670332,
                "90.0" : 23.551017415395243,
                "95.0" : 23.593799119415422,
                "99.0" : 23.595783588217536,
                "99.9" : 23.595783588217536,
                "99.99" : 23.595783588217536,
                "99.999" : 23.595783588217536,
                "99.9999" : 23.595783588217536,
                "100.0" : 23.595783588217536
            },
            "scoreUnit" : "ops/ms",
            "rawData" : [
                [
                    23.414336357358675,
                    23.13684461427701,
                    23.421088927924846,
                    23.44263345452038,
                    23.465040581336293,
                    23.505326244374913,
                    23.4296005483995,
                    23.595783588217536,
                    23.432458732675734,
                    23.55609421217528
                ],
                [
                    23.39840776972711,
                    23.221464727752537,
                    23.378005583679524,
                    23.25353948873969,
                    23.221440170627965,
                    23.246106895046253,
                    23.35327381399079,
                    23.273328435929432,
                    23.367135303804567,
                    22.699096518954484
                ]
            ]
        },
        "secondaryMetrics" : {
        }
    },
    {
        "jmhVersion" : "1.35",
        "benchmark" : "javalin.performance.JavalinBenchmark.routes10",
        "mode" : "thrpt",
        "threads" : 4,
        "forks" : 2,
        "jvm" : "/usr/lib/jvm/temurin-17-jdk-amd64/bin/java",
        "jvmArgs" : [
            "-Dforks=2",
            "-DiterationTime=1000",
            "-Diterations=10",
            "-Dmode=benchmark",
            "-DprofileName",
            "-DresultFormat=json",
            "-Dthreads=4",
            "-Dversion=7.0.1",
            "-Dfile.encoding=UTF-8",
            "-Duser.country",
            "-Duser.language=en",
            "-Duser.variant"
        ],
        "jdkVersion" : "17.0.18",
        "vmName" : "OpenJDK 64-Bit Server VM",
        "vmVersion" : "17.0.18+8",
        "warmupIterations" : 10,
        "warmupTime" : "1000 ms",
        "warmupBatchSize" : 1,
        "measurementIterations" : 10,
        "measurementTime" : "1000 ms",
        "measurementBatchSize" : 1,
        "primaryMetric" : {
            "score" : 21.445461179985188,
            "scoreError" : 0.29331295105838745,
            "scoreConfidence" : [
                21.1521482289268,
                21.738774131043574
            ],
            "scorePercentiles" : {
                "0.0" : 20.135805134256135,
                "50.0" : 21.5182405942915,
                "90.0" : 21.700985531726488,
                "95.0" : 21.708294439012025,
                "99.0" : 21.708516854210007,
                "99.9" : 21.708516854210007,
                "99.99" : 21.708516854210007,
                "99.999" : 21.708516854210007,
                "99.9999" : 21.708516854210007,
                "100.0" : 21.708516854210007
            },
            "scoreUnit" : "ops/ms",
            "rawData" : [
                [
                    21.569905486937778,
                    21.55367586654043,
                    21.57135681284324,
                    21.708516854210007,
                    21.600747216443825,
                    21.499287107647305,
                    21.537194080935695,
                    21.673238365011425,
                    21.704068550250383,
                    21.645699875983944
                ],
                [
                    21.556710072414546,
                    21.37868096912261,
                    20.135805134256135,
                    21.43681169129816,
                    21.474956019769245,
                    21.47508161594657,
                    21.490656717447205,
                    21.09989972885952,
                    21.37062209959638,
                    21.426309334189273
                ]
            ]
        },
        "secondaryMetrics" : {
        }
    },
    {
        "jmhVersion" : "1.35",
        "benchmark" : "javalin.performance.JavalinBenchmark.routes100",
        "mode" : "thrpt",
        "threads" : 4,
        "forks" : 2,
        "jvm" : "/usr/lib/jvm/temurin-17-jdk-amd64/bin/java",
        "jvmArgs" : [
            "-Dforks=2",
            "-DiterationTime=1000",
            "-Diterations=10",
            "-Dmode=benchmark",
            "-DprofileName",
            "-DresultFormat=json",
            "-Dthreads=4",
            "-Dversion=7.0.1",
            "-Dfile.encoding=UTF-8",
            "-Duser.country",
            "-Duser.language=en",
            "-Duser.variant"
        ],
        "jdkVersion" : "17.0.18",
        "vmName" : "OpenJDK 64-Bit Server VM",
        "vmVersion" : "17.0.18+8",
        "warmupIterations" : 10,
        "warmupTime" : "1000 ms",
        "warmupBatchSize" : 1,
        "measurementIterations" : 10,
        "measurementTime" : "1000 ms",
        "measurementBatchSize" : 1,
        "primaryMetric" : {
            "score" : 16.924292744829025,
            "scoreError" : 0.10303566925845918,
            "scoreConfidence" : [
                16.821257075570564,
                17.027328414087485
            ],
            "scorePercentiles" : {
                "0.0" : 16.553821878655715,
                "50.0" : 16.931751279999666,
                "90.0" : 17.057410106897677,
                "95.0" : 17.08980882597062,
                "99.0" : 17.091502272736214,
                "99.9" : 17.091502272736214,
                "99.99" : 17.091502272736214,
                "99.999" : 17.091502272736214,
                "99.9999" : 17.091502272736214,
                "100.0" : 17.091502272736214
            },
            "scoreUnit" : "ops/ms",
            "rawData" : [
                [
                    16.991703288103235,
                    16.948740139284087,
                    17.00362084844559,
                    17.091502272736214,
                    17.044932591184683,
                    16.895253097383268,
                    17.05763333742434,
                    17.055401032157746,
                    16.979577513271643,
                    16.94228493550319
                ],
                [
                    16.928533510431674,
                    16.894583197535503,
                    16.927628402286082,
                    16.829404251804682,
                    16.553821878655715,
                    16.90516614589444,
                    16.812923747863103,
                    16.934969049567663,
                    16.871038823249705,
                    16.817136833797996
                ]
            ]
        },
        "secondaryMetrics" : {
        }
    },
    {
        "jmhVersion" : "1.35",
        "benchmark" : "javalin.performance.JavalinBenchmark.routes1000",
        "mode" : "thrpt",
        "threads" : 4,
        "forks" : 2,
        "jvm" : "/usr/lib/jvm/temurin-17-jdk-amd64/bin/java",
        "jvmArgs" : [
            "-Dforks=2",
            "-DiterationTime=1000",
            "-Diterations=10",
            "-Dmode=benchmark",
            "-DprofileName",
            "-DresultFormat=json",
            "-Dthreads=4",
            "-Dversion=7.0.1",
            "-Dfile.encoding=UTF-8",
            "-Duser.country",
            "-Duser.language=en",
            "-Duser.variant"
        ],
        "jdkVersion" : "17.0.18",
        "vmName" : "OpenJDK 64-Bit Server VM",
        "vmVersion" : "17.0.18+8",
        "warmupIterations" : 10,
        "warmupTime" : "1000 ms",
        "warmupBatchSize" : 1,
        "measurementIterations" : 10,
        "measurementTime" : "1000 ms",
        "measurementBatchSize" : 1,
        "primaryMetric" : {
            "score" : 4.923812707070248,
            "scoreError" : 0.08897077123199058,
            "scoreConfidence" : [
                4.8348419358382575,
                5.012783478302239
            ],
            "scorePercentiles" : {
                "0.0" : 4.747682443442848,
                "50.0" : 4.900877897929811,
                "90.0" : 5.05477685910864,
                "95.0" : 5.068275816530027,
                "99.0" : 5.068880844637348,
                "99.9" : 5.068880844637348,
                "99.99" : 5.068880844637348,
                "99.999" : 5.068880844637348,
                "99.9999" : 5.068880844637348,
                "100.0" : 5.068880844637348
            },
            "scoreUnit" : "ops/ms",
            "rawData" : [
                [
                    4.867168418435373,
                    4.862552264192831,
                    4.759066376540808,
                    4.868331758903093,
                    4.823382983209299,
                    4.747682443442848,
                    4.807289164857561,
                    4.874093693073527,
                    4.865668253081523,
                    4.861432578601306
                ],
                [
                    5.006568711911795,
                    5.033966302032246,
                    5.03674604866811,
                    5.019894547831513,
                    4.927662102786095,
                    4.958618069456227,
                    5.056780282490921,
                    5.004925295674082,
                    5.025544001578455,
                    5.068880844637348
                ]
            ]
        },
        "secondaryMetrics" : {
        }
    },
    {
        "jmhVersion" : "1.35",
        "benchmark" : "javalin.performance.JavalinBenchmark.routes10000",
        "mode" : "thrpt",
        "threads" : 4,
        "forks" : 2,
        "jvm" : "/usr/lib/jvm/temurin-17-jdk-amd64/bin/java",
        "jvmArgs" : [
            "-Dforks=2",
            "-DiterationTime=1000",
            "-Diterations=10",
            "-Dmode=benchmark",
            "-DprofileName",
            "-DresultFormat=json",
            "-Dthreads=4",
            "-Dversion=7.0.1",
            "-Dfile.encoding=UTF-8",
            "-Duser.country",
            "-Duser.language=en",
            "-Duser.variant"
        ],
        "jdkVersion" : "17.0.18",
        "vmName" : "OpenJDK 64-Bit Server VM",
        "vmVersion" : "17.0.18+8",
        "warmupIterations" : 10,
        "warmupTime" : "1000 ms",
        "warmupBatchSize" : 1,
        "measurementIterations" : 10,
        "measurementTime" : "1000 ms",
        "measurementBatchSize" : 1,
        "primaryMetric" : {
            "score" : 0.6284135258211274,
            "scoreError" : 0.023308939671285587,
            "scoreConfidence" : [
                0.6051045861498419,
                0.651722465492413
            ],
            "scorePercentiles" : {
                "0.0" : 0.5730182745548412,
                "50.0" : 0.6279195121045946,
                "90.0" : 0.6679166405085913,
                "95.0" : 0.6713629998579358,
                "99.0" : 0.6715120800732857,
                "99.9" : 0.6715120800732857,
                "99.99" : 0.6715120800732857,
                "99.999" : 0.6715120800732857,
                "99.9999" : 0.6715120800732857,
                "100.0" : 0.6715120800732857
            },
            "scoreUnit" : "ops/ms",
            "rawData" : [
                [
                    0.5945746118371118,
                    0.6152035029180186,
                    0.6571011404725448,
                    0.617209894165361,
                    0.6335536691042551,
                    0.6617074524739862,
                    0.6107818487155834,
                    0.6715120800732857,
                    0.6297045673462404,
                    0.6447052808893837
                ],
                [
                    0.6222646703387412,
                    0.5974965113126566,
                    0.6192248162684637,
                    0.5730182745548412,
                    0.6623921231893162,
                    0.6261344568629488,
                    0.6323526973404894,
                    0.6685304757662885,
                    0.6324533769651395,
                    0.59834906582789
                ]
            ]
        },
        "secondaryMetrics" : {
        }
    },
    {
        "jmhVersion" : "1.35",
        "benchmark" : "javalin.performance.JavalinBenchmark.staticFile100kb",
        "mode" : "thrpt",
        "threads" : 4,
        "forks" : 2,
        "jvm" : "/usr/lib/jvm/temurin-17-jdk-amd64/bin/java",
        "jvmArgs" : [
            "-Dforks=2",
            "-DiterationTime=1000",
            "-Diterations=10",
            "-Dmode=benchmark",
            "-DprofileName",
            "-DresultFormat=json",
            "-Dthreads=4",
            "-Dversion=7.0.1",
            "-Dfile.encoding=UTF-8",
            "-Duser.country",
            "-Duser.language=en",
            "-Duser.variant"
        ],
        "jdkVersion" : "17.0.18",
        "vmName" : "OpenJDK 64-Bit Server VM",
        "vmVersion" : "17.0.18+8",
        "warmupIterations" : 10,
        "warmupTime" : "1000 ms",
        "warmupBatchSize" : 1,
        "measurementIterations" : 10,
        "measurementTime" : "1000 ms",
        "measurementBatchSize" : 1,
        "primaryMetric" : {
            "score" : 2.7596353123387987,
            "scoreError" : 0.013292645529176625,
            "scoreConfidence" : [
                2.746342666809622,
                2.7729279578679753
            ],
            "scorePercentiles" : {
                "0.0" : 2.7219896962334835,
                "50.0" : 2.7623246045860204,
                "90.0" : 2.7799850562816766,
                "95.0" : 2.7806470496030866,
                "99.0" : 2.780672038654899,
                "99.9" : 2.780672038654899,
                "99.99" : 2.780672038654899,
                "99.999" : 2.780672038654899,
                "99.9999" : 2.780672038654899,
                "100.0" : 2.780672038654899
            },
            "scoreUnit" : "ops/ms",
            "rawData" : [
                [
                    2.758871640400524,
                    2.7219896962334835,
                    2.7369558873200805,
                    2.7348926391835784,
                    2.766848116394522,
                    2.7783002442488436,
                    2.7801722576186583,
                    2.7584903377882712,
                    2.7588060241547363,
                    2.7701598307735757
                ],
                [
                    2.7685502248274223,
                    2.755426105874659,
                    2.7564936657151895,
                    2.750171513710936,
                    2.780672038654899,
                    2.765777568771517,
                    2.7485131812972554,
                    2.767758960290548,
                    2.7667994712836794,
                    2.767056842233589
                ]
            ]
        },
        "secondaryMetrics" : {
        }
    },
    {
        "jmhVersion" : "1.35",
        "benchmark" : "javalin.performance.JavalinBenchmark.staticFile1mb",
        "mode" : "thrpt",
        "threads" : 4,
        "forks" : 2,
        "jvm" : "/usr/lib/jvm/temurin-17-jdk-amd64/bin/java",
        "jvmArgs" : [
            "-Dforks=2",
            "-DiterationTime=1000",
            "-Diterations=10",
            "-Dmode=benchmark",
            "-DprofileName",
            "-DresultFormat=json",
            "-Dthreads=4",
            "-Dversion=7.0.1",
            "-Dfile.encoding=UTF-8",
            "-Duser.country",
            "-Duser.language=en",
            "-Duser.variant"
        ],
        "jdkVersion" : "17.0.18",
        "vmName" : "OpenJDK 64-Bit Server VM",
        "vmVersion" : "17.0.18+8",
        "warmupIterations" : 10,
        "warmupTime" : "1000 ms",
        "warmupBatchSize" : 1,
        "measurementIterations" : 10,
        "measurementTime" : "1000 ms",
        "measurementBatchSize" : 1,
        "primaryMetric" : {
            "score" : 0.3285950621046756,
            "scoreError" : 0.009773504777485054,
            "scoreConfidence" : [
                0.31882155732719053,
                0.33836856688216066
            ],
            "scorePercentiles" : {
                "0.0" : 0.30696133306313933,
                "50.0" : 0.3317382547834288,
                "90.0" : 0.3427665103642642,
                "95.0" : 0.345126389487696,
                "99.0" : 0.34524605413114995,
                "99.9" : 0.34524605413114995,
                "99.99" : 0.34524605413114995,
                "99.999" : 0.34524605413114995,
                "99.9999" : 0.34524605413114995,
                "100.0" : 0.34524605413114995
            },
            "scoreUnit" : "ops/ms",
            "rawData" : [
                [
                    0.3214129355757456,
                    0.33018116610280457,
                    0.3316388092941505,
                    0.331837700272707,
                    0.3385584465680692,
                    0.33408767308245174,
                    0.30696133306313933,
                    0.30731011560063953,
                    0.34285276126207076,
                    0.33236522159745907
                ],
                [
                    0.32451899332771234,
                    0.31958282804951843,
                    0.3324550209521287,
                    0.3245635926981234,
                    0.33972098434087955,
                    0.33461464315084355,
                    0.31497010254315777,
                    0.3170326081967554,
                    0.34524605413114995,
                    0.34199025228400526
                ]
            ]
        },
        "secondaryMetrics" : {
        }
    }
]


